scss/__init__.py
scss/base.py
scss/compat.py
scss/control.py
scss/function.py
scss/grammar.py
scss/parser.py
scss/tool.py
scss/value.py
scss/tests/__init__.py
scss/tests/test_color_functions.py
scss/tests/test_extend.py
scss/tests/test_fake.py
scss/tests/test_files.py
scss/tests/test_font_face.py
scss/tests/test_for.py
scss/tests/test_functions.py
scss/tests/test_if.py
scss/tests/test_mixin.py
scss/tests/test_nesting.py
scss/tests/test_options.py
scss/tests/test_scss.py
scss/tests/test_variables.py
scss-0.8.73.dist-info/DESCRIPTION.rst
scss-0.8.73.dist-info/entry_points.txt
scss-0.8.73.dist-info/METADATA
scss-0.8.73.dist-info/metadata.json
scss-0.8.73.dist-info/RECORD
scss-0.8.73.dist-info/top_level.txt
scss-0.8.73.dist-info/WHEEL
