Metadata-Version: 1.1
Name: scss
Version: 0.8.73
Summary: Python-scss is SCSS compiler for Python. See http://sass-lang.com for more information about scss syntax.
